odoo/addons/product_uom_updatable/README.rst
odoo/addons/product_uom_updatable/__init__.py
odoo/addons/product_uom_updatable/__manifest__.py
odoo/addons/product_uom_updatable/i18n/product_uom_updatable.pot
odoo/addons/product_uom_updatable/models/__init__.py
odoo/addons/product_uom_updatable/models/product_template.py
odoo/addons/product_uom_updatable/readme/CONTRIBUTORS.rst
odoo/addons/product_uom_updatable/readme/CREDITS.rst
odoo/addons/product_uom_updatable/readme/DESCRIPTION.rst
odoo/addons/product_uom_updatable/static/description/icon.png
odoo/addons/product_uom_updatable/static/description/index.html
odoo/addons/product_uom_updatable/tests/__init__.py
odoo/addons/product_uom_updatable/tests/test_product_uom_update.py
odoo14_addon_product_uom_updatable-14.0.1.0.1.dist-info/METADATA
odoo14_addon_product_uom_updatable-14.0.1.0.1.dist-info/WHEEL
odoo14_addon_product_uom_updatable-14.0.1.0.1.dist-info/top_level.txt
odoo14_addon_product_uom_updatable-14.0.1.0.1.dist-info/RECORD
