Metadata-Version: 2.1
Name: odoo14-addon-product-uom-updatable
Version: 14.0.1.0.1
Summary: allows products uom to be modified after be used in a stock picking if the product uom is of the same category
Home-page: https://github.com/OCA/product-attribute
Author: ACSONE SA/NV, Camptocamp, Odoo Community Association (OCA)
Author-email: support@odoo-community.org
License: AGPL-3
Platform: UNKNOWN
Classifier: Programming Language :: Python
Classifier: Framework :: Odoo
Classifier: License :: OSI Approved :: GNU Affero General Public License v3
Requires-Python: >=3.6
Requires-Dist: odoo (<14.1dev,>=14.0a)
